glove80_visualizer/__init__.py
glove80_visualizer/cli.py
glove80_visualizer/colors.py
glove80_visualizer/config.py
glove80_visualizer/extractor.py
glove80_visualizer/kle_renderer.py
glove80_visualizer/kle_template.py
glove80_visualizer/models.py
glove80_visualizer/parser.py
glove80_visualizer/pdf_generator.py
glove80_visualizer/svg_generator.py
glove80_keymap_visualizer-0.6.0.dist-info/METADATA
glove80_keymap_visualizer-0.6.0.dist-info/WHEEL
glove80_keymap_visualizer-0.6.0.dist-info/entry_points.txt
glove80_keymap_visualizer-0.6.0.dist-info/licenses/LICENSE
glove80_keymap_visualizer-0.6.0.dist-info/RECORD
