Metadata-Version: 2.4
Name: glove80-keymap-visualizer
Version: 0.6.0
Summary: Generate PDF visualizations of Glove80 keyboard layers from ZMK keymap files
Project-URL: Homepage, https://github.com/dsifry/glove80-keymap-visualizer
Project-URL: Repository, https://github.com/dsifry/glove80-keymap-visualizer
Project-URL: Issues, https://github.com/dsifry/glove80-keymap-visualizer/issues
Author: Dave Sifry
License: MIT
License-File: LICENSE
Keywords: glove80,keyboard,keymap,pdf,visualization,zmk
Classifier: Development Status :: 3 - Alpha
Classifier: Intended Audience :: End Users/Desktop
Classifier: License :: OSI Approved :: MIT License
Classifier: Programming Language :: Python :: 3
Classifier: Programming Language :: Python :: 3.10
Classifier: Programming Language :: Python :: 3.11
Classifier: Programming Language :: Python :: 3.12
Classifier: Programming Language :: Python :: 3.13
Classifier: Topic :: Utilities
Requires-Python: >=3.10
Requires-Dist: cairosvg<3.0.0,>=2.7.0
Requires-Dist: click<9.0.0,>=8.0.0
Requires-Dist: keymap-drawer<0.19.0,>=0.18.0
Requires-Dist: pikepdf<10.0.0,>=8.0.0
Requires-Dist: pyyaml<7.0.0,>=6.0.0
Provides-Extra: dev
Requires-Dist: black>=23.0.0; extra == 'dev'
Requires-Dist: build>=1.0.0; extra == 'dev'
Requires-Dist: mypy>=1.0.0; extra == 'dev'
Requires-Dist: playwright>=1.40.0; extra == 'dev'
Requires-Dist: pytest-cov>=4.0.0; extra == 'dev'
Requires-Dist: pytest-mock>=3.10.0; extra == 'dev'
Requires-Dist: pytest>=7.0.0; extra == 'dev'
Requires-Dist: ruff>=0.1.0; extra == 'dev'
Requires-Dist: toon-python>=0.1.0; extra == 'dev'
Requires-Dist: types-pyyaml>=6.0.0; extra == 'dev'
